{
  "floors": [
    { "x": 5, "z": 5, "width": 1, "height": 1.5, "depth": 1 },
    { "x": -5, "z": -3, "width": 1, "height": 2, "depth": 1 },
    {
      "x": 0,
      "y": -0.5,
      "z": 0,
      "width": 50,
      "height": 1,
      "depth": 50,
      "color": "#fff5e1",
      "texturePath": "/assets/images/textures/wood_floor6.jpg"
    }
  ],
  "rooms": [
    {
      "x": 0,
      "z": 0,
      "width": 12,
      "depth": 26,
      "doors": [
        { "wall": "west", "position": -6 },
        { "wall": "east", "position": 6 }
      ]
    },
    {
      "x": -12.01,
      "z": -6.01,
      "width": 12,
      "depth": 26,
      "doors": [
        { "wall": "east", "position": 0 },
        { "wall": "south", "position": 0 }
      ]
    },
    {
      "x": 12.01,
      "z": 6.01,
      "width": 12,
      "depth": 12,
      "doors": [{ "wall": "west", "position": 0 }]
    }
  ],
  "paintings": [
    {
      "imagePath": "/assets/images/paintings/life.png",
      "position": { "x": -17.74, "y": 1.6, "z": -4 },
      "width": 2,
      "height": 2,
      "orientation": "west"
    }
  ],
  "spotlights": [
    {
      "color": "#ffffff",
      "intensity": 50,
      "distance": 20,
      "angle": 0.523599,
      "penumbra": 0.5,
      "decay": 2,
      "position": { "x": 3, "y": 5, "z": 3 },
      "target": { "x": 0, "y": 0, "z": 0 }
    },
    {
      "color": "#ffffff",
      "intensity": 50,
      "distance": 20,
      "angle": 0.523599,
      "penumbra": 0.5,
      "decay": 2,
      "position": { "x": 0, "y": 5, "z": 0 },
      "target": { "x": -3, "y": 0, "z": -3 }
    },
    {
      "color": "#ffffff",
      "intensity": 25,
      "distance": 8,
      "angle": 0.523599,
      "penumbra": 0.5,
      "decay": 2,
      "position": { "x": -14.54, "y": 5, "z": -4 },
      "target": { "x": -17.54, "y": 1.6, "z": -4 }
    }
  ],
  "items": [
    { "x": 2, "y": 1, "z": 2, "type": "painting" },
    { "x": -2, "y": 1, "z": -2, "type": "guard" }
  ]
}
